.gitignore
CHANGELOG.rst
CONTRIBUTING.rst
LICENSE.txt
README.rst
pytest.ini
setup.py
test_requirements.txt
binarymap/__init__.py
binarymap/binarymap.py
binarymap.egg-info/PKG-INFO
binarymap.egg-info/SOURCES.txt
binarymap.egg-info/dependency_links.txt
binarymap.egg-info/requires.txt
binarymap.egg-info/top_level.txt
docs/.nojekyll
docs/Makefile
docs/README.rst
docs/acknowledgments.rst
docs/conf.py
docs/doc_requirements.txt
docs/index.rst
docs/installation.rst
docs/package_index.rst
docs/_static/BloomLogo.jpg