Metadata-Version: 2.1
Name: binarymap
Version: 0.8
Summary: Binary representation of protein or nucleotide sequences.
Home-page: https://github.com/jbloomlab/binarymap
Download-URL: https://github.com/jbloomlab/binarymap/tarball/0.8
Author: `the Bloom lab <https://jbloomlab.org>`_
Author-email: jbloom@fredhutch.org
License: GPLv3
Platform: Linux and Mac OS X.
License-File: LICENSE.txt
Requires-Dist: natsort>=0.8
Requires-Dist: pandas>=1.2
Requires-Dist: scipy>=1.1
